{
  "scan_datum": "2026-04-18T08:15:08.360829",
  "totaal_gescand": 1016,
  "na_filter": 989,
  "kansen": [
    {
      "adres": "Oranjelaan 57",
      "stad": "Dordrecht",
      "postcode": "3311DH",
      "wijk": "Kasperspad en omgeving",
      "prijs": 269000,
      "opp_m2": 116,
      "prijs_per_m2": 2319.0,
      "type_woning": "apartment",
      "bouwjaar": 1929,
      "energie_label": "C",
      "kamers": 4,
      "source": "funda",
      "url": "https://www.funda.nl/detail/koop/dordrecht/oranjelaan-57/43303844/",
      "foto_url": "https://cloud.funda.nl/valentina_media/227/102/898.jpg",
      "foto_urls": [
        "https://cloud.funda.nl/valentina_media/227/102/898.jpg",
        "https://cloud.funda.nl/valentina_media/227/102/915.jpg",
        "https://cloud.funda.nl/valentina_media/227/103/130.jpg",
        "https://cloud.funda.nl/valentina_media/227/102/909.jpg",
        "https://cloud.funda.nl/valentina_media/227/102/903.jpg",
        "https://cloud.funda.nl/valentina_media/227/103/104.jpg"
      ],
      "strategie": "fix_flip",
      "marge_pct": 34.0,
      "winst_euro": 190505,
      "roi_pct": 51.4,
      "totale_kosten": 370410,
      "verwachte_opbrengst": 560916,
      "score": 6,
      "is_opknapper": false,
      "calc": {
        "vraagprijs": 269000,
        "ovb_pct": 8.0,
        "ovb": 21520,
        "notaris_makelaar_aankoop": 3497,
        "aankoop_totaal": 294017,
        "renovatie_per_m2": 583,
        "renovatie_detail": {
          "componenten": [
            {
              "naam": "Keuken renovatie",
              "kosten": 14000,
              "reden": "Nieuwe fronten, apparatuur, blad, tegelwerk"
            },
            {
              "naam": "Badkamer renovatie",
              "kosten": 12000,
              "reden": "Nieuwe tegels, sanitair, kranen"
            },
            {
              "naam": "Toilet opknappen",
              "kosten": 2500,
              "reden": "Nieuwe WC pot, fontein, kleine tegelreparaties"
            },
            {
              "naam": "Vloeren (60/m²)",
              "kosten": 6960,
              "reden": "PVC click vloer leggen (licht egaliseren)"
            },
            {
              "naam": "Schilderwerk (20/m²)",
              "kosten": 2320,
              "reden": "Latex muren en plafonds"
            },
            {
              "naam": "Elektra upgraden",
              "kosten": 3500,
              "reden": "Groepenkast + extra groepen + stopcontacten"
            },
            {
              "naam": "Isolatie verbeteren",
              "kosten": 4640,
              "reden": "Label C: dak + vloer bijwerken"
            },
            {
              "naam": "Ramen deels (7x)",
              "kosten": 8400,
              "reden": "Oudere ramen upgraden naar HR++"
            },
            {
              "naam": "CV-ketel onderhoud/reserve",
              "kosten": 1500,
              "reden": "Mogelijk verouderd, budget voor vervanging"
            },
            {
              "naam": "Buitenschilderwerk",
              "kosten": 2500,
              "reden": "Kozijnen buiten schilderen"
            },
            {
              "naam": "Onvoorzien (10%)",
              "kosten": 5832,
              "reden": "Buffer voor verrassingen (asbest, fundering, verborgen gebreken)"
            },
            {
              "naam": "Architect + leges (6%)",
              "kosten": 3499,
              "reden": "Ontwerp, vergunning, bouwbegeleiding"
            }
          ],
          "totaal": 67651,
          "per_m2": 583,
          "onvoorzien_pct": 10
        },
        "bouw_totaal": 67651,
        "looptijd_maanden": 4,
        "rente_pct": 8.0,
        "financiering_basis": 327842,
        "rente": 8742,
        "totaal_kosten": 370410,
        "verkoop_m2": 4931,
        "verkoop_bron": "referentie",
        "referenties": [
          {
            "adres": "Kromhout 230",
            "prijs": 615000,
            "opp_m2": 104,
            "prijs_per_m2": 5913,
            "energie_label": "B",
            "type": "apartment",
            "wijk": "Kasperspad en omgeving",
            "url": "https://www.funda.nl/detail/koop/dordrecht/appartement-kromhout-230/89769037/"
          },
          {
            "adres": "Kromhout 39",
            "prijs": 410000,
            "opp_m2": 81,
            "prijs_per_m2": 5062,
            "energie_label": "A",
            "type": "apartment",
            "wijk": "Matena's Pad en omgeving",
            "url": "https://www.funda.nl/detail/koop/dordrecht/appartement-kromhout-39/43354248/"
          },
          {
            "adres": "Kromhout 41",
            "prijs": 525000,
            "opp_m2": 107,
            "prijs_per_m2": 4907,
            "energie_label": "A",
            "type": "apartment",
            "wijk": "Matena's Pad en omgeving",
            "url": "https://www.funda.nl/detail/koop/dordrecht/appartement-kromhout-41/43365320/"
          },
          {
            "adres": "Merwekade 85",
            "prijs": 495000,
            "opp_m2": 105,
            "prijs_per_m2": 4714,
            "energie_label": "B",
            "type": "apartment",
            "wijk": "Bleijenhoek",
            "url": "https://www.funda.nl/detail/koop/dordrecht/appartement-merwekade-85/43303970/"
          },
          {
            "adres": "Sint Jacobsplein 44",
            "prijs": 425000,
            "opp_m2": 91,
            "prijs_per_m2": 4670,
            "energie_label": "A",
            "type": "apartment",
            "wijk": "Groenmarkt en omgeving",
            "url": "https://www.funda.nl/detail/koop/dordrecht/appartement-sint-jacobsplein-44/43317990/"
          }
        ],
        "bruto_verkoopprijs": 571996,
        "makelaar_verkoop": 8579,
        "notaris_verkoop": 2500,
        "verkoop_kosten": 11079,
        "netto_opbrengst": 560916,
        "winst": 190505,
        "marge_pct": 34.0,
        "roi_pct": 51.4,
        "bod_korting_pct": 10,
        "bod": 242100,
        "bod_totaal_investering": 340224,
        "bod_winst": 220691,
        "bod_marge_pct": 39.3,
        "splitsen": {
          "mag_splitsen": true,
          "uitleg": "Splitsen is waarschijnlijk toegestaan in Dordrecht. Oppervlak (116m2) voldoet aan minimum (100m2). Per unit: 58m2 (min: 24m2). Vereist: splitsingsvergunning.",
          "vergunning": "splitsingsvergunning",
          "min_opp_m2": 100,
          "max_units": 3,
          "min_per_unit_m2": 24,
          "opp_per_unit": 58.0,
          "bijzonderheden": "Splitsingsvergunning vereist. Min 100m2 totaal, max 3 units. In eiland van Dordrecht: beschermd stadsgezicht."
        },
        "opbouwen": {
          "mag_opbouwen": null,
          "uitleg": "Geen opbouwbeleid bekend voor Dordrecht. Check het bestemmingsplan op ruimtelijkeplannen.nl.",
          "max_hoogte_m": null,
          "max_verdiepingen": null,
          "dakopbouw_toegestaan": null,
          "ruimte_over_m": null,
          "bijzonderheden": ""
        },
        "looptijd_detail": {
          "totaal_maanden": 4,
          "vergunning_maanden": 0,
          "verbouw_maanden": 2.2,
          "verkoop_maanden": 2,
          "type": "cosmetisch"
        },
        "funda_prijs_per_m2": "€ 2.319",
        "foto_urls": [
          "https://cloud.funda.nl/valentina_media/227/102/898.jpg",
          "https://cloud.funda.nl/valentina_media/227/102/915.jpg",
          "https://cloud.funda.nl/valentina_media/227/103/130.jpg",
          "https://cloud.funda.nl/valentina_media/227/102/909.jpg",
          "https://cloud.funda.nl/valentina_media/227/102/903.jpg",
          "https://cloud.funda.nl/valentina_media/227/103/104.jpg"
        ],
        "has_garden": false,
        "has_balcony": true,
        "has_roof_terrace": false,
        "has_parking_on_site": false,
        "has_solar_panels": false,
        "has_heat_pump": false,
        "is_monument": false,
        "beschrijving_parsed": {
          "vve_bijdrage": 240.0
        },
        "vve_bijdrage": 240.0,
        "validatie": {
          "goedgekeurd": false,
          "onze_pm2": 4931,
          "bronnen": {
            "funda_pm2": 2319
          },
          "gem_extern_pm2": 2319,
          "afwijking_pct": 112.6,
          "gecorrigeerde_pm2": 2435,
          "reden": "Onze prijs 113% hoger dan extern (2319/m2). Gecorrigeerd naar 2435/m2"
        }
      }
    },
    {
      "adres": "Dotterbloemstraat 5",
      "stad": "Rotterdam",
      "postcode": "3053 JV",
      "wijk": "Schiebroek",
      "prijs": 225000,
      "opp_m2": 116,
      "prijs_per_m2": 1940,
      "type_woning": "",
      "bouwjaar": 0,
      "energie_label": "",
      "kamers": 0,
      "source": "mkl_kolpa",
      "url": "https://www.kolpa.nl/aanbod/rotterdam/dotterbloemstraat-5c/69676fa66285544622a438b1",
      "foto_url": "",
      "foto_urls": [],
      "strategie": "fix_flip",
      "marge_pct": 33.3,
      "winst_euro": 178678,
      "roi_pct": 49.9,
      "totale_kosten": 357899,
      "verwachte_opbrengst": 536578,
      "score": 6,
      "is_opknapper": false,
      "calc": {
        "vraagprijs": 225000,
        "ovb_pct": 8.0,
        "ovb": 18000,
        "notaris_makelaar_aankoop": 2925,
        "aankoop_totaal": 245925,
        "renovatie_per_m2": 847,
        "renovatie_detail": {
          "componenten": [
            {
              "naam": "Keuken renovatie",
              "kosten": 14000,
              "reden": "Nieuwe fronten, apparatuur, blad, tegelwerk"
            },
            {
              "naam": "Badkamer renovatie",
              "kosten": 12000,
              "reden": "Nieuwe tegels, sanitair, kranen"
            },
            {
              "naam": "Toilet opknappen",
              "kosten": 2500,
              "reden": "Nieuwe WC pot, fontein, kleine tegelreparaties"
            },
            {
              "naam": "Vloeren (70/m²)",
              "kosten": 8120,
              "reden": "Egaliseren + PVC click vloer leggen"
            },
            {
              "naam": "Schilderwerk (35/m²)",
              "kosten": 4060,
              "reden": "Latex muren+plafonds + binnenkozijnen schilderen"
            },
            {
              "naam": "Elektra upgraden",
              "kosten": 3500,
              "reden": "Groepenkast + extra groepen + stopcontacten"
            },
            {
              "naam": "Leidingwerk aanpassen",
              "kosten": 2000,
              "reden": "Verouderd leidingwerk bijwerken"
            },
            {
              "naam": "Isolatie (dak+vloer+spouw)",
              "kosten": 8700,
              "reden": "Label ?: dak 3190, vloer 3480, spouw 2029"
            },
            {
              "naam": "Ramen HR++ (14x)",
              "kosten": 21000,
              "reden": "Enkel/dubbel glas naar HR++ incl nieuwe kozijnen"
            },
            {
              "naam": "CV-ketel nieuw (HR-combi)",
              "kosten": 2200,
              "reden": "Nieuwe HR-combi ketel incl installatie"
            },
            {
              "naam": "Radiatoren (7x)",
              "kosten": 1260,
              "reden": "Oude radiatoren vervangen (7 stuks)"
            },
            {
              "naam": "Buitenschilderwerk",
              "kosten": 2500,
              "reden": "Kozijnen buiten schilderen"
            },
            {
              "naam": "Onvoorzien (12%)",
              "kosten": 9820,
              "reden": "Buffer voor verrassingen (asbest, fundering, verborgen gebreken)"
            },
            {
              "naam": "Architect + leges (8%)",
              "kosten": 6547,
              "reden": "Ontwerp, vergunning, bouwbegeleiding"
            }
          ],
          "totaal": 98207,
          "per_m2": 847,
          "onvoorzien_pct": 12
        },
        "bouw_totaal": 98207,
        "looptijd_maanden": 7,
        "rente_pct": 8.0,
        "financiering_basis": 295028,
        "rente": 13767,
        "totaal_kosten": 357899,
        "verkoop_m2": 4718,
        "verkoop_bron": "referentie",
        "referenties": [
          {
            "adres": "Aronskelkstraat 161",
            "prijs": 529000,
            "opp_m2": 104,
            "prijs_per_m2": 5087,
            "energie_label": "A",
            "type": "apartment",
            "wijk": "Schiebroek",
            "url": "https://www.funda.nl/detail/koop/rotterdam/appartement-aronskelkstraat-161/43351965/"
          },
          {
            "adres": "Kastanjesingel 73",
            "prijs": 469000,
            "opp_m2": 100,
            "prijs_per_m2": 4690,
            "energie_label": "C",
            "type": "apartment",
            "wijk": "Schiebroek",
            "url": "https://www.funda.nl/detail/koop/rotterdam/appartement-kastanjesingel-73-b/89771568/"
          },
          {
            "adres": "Kastanjesingel 98",
            "prijs": 359000,
            "opp_m2": 82,
            "prijs_per_m2": 4378,
            "energie_label": "F",
            "type": "apartment",
            "wijk": "Schiebroek",
            "url": "https://www.funda.nl/detail/koop/rotterdam/appartement-kastanjesingel-98-b/43221889/"
          }
        ],
        "bruto_verkoopprijs": 547288,
        "makelaar_verkoop": 8209,
        "notaris_verkoop": 2500,
        "verkoop_kosten": 10709,
        "netto_opbrengst": 536578,
        "winst": 178678,
        "marge_pct": 33.3,
        "roi_pct": 49.9,
        "bod_korting_pct": 10,
        "bod": 202500,
        "bod_totaal_investering": 332159,
        "bod_winst": 204418,
        "bod_marge_pct": 38.1,
        "splitsen": {
          "mag_splitsen": true,
          "uitleg": "Splitsen is waarschijnlijk toegestaan in Rotterdam. Oppervlak (116m2) voldoet aan minimum (80m2). Per unit: 58m2 (min: 18m2). Vereist: splitsingsvergunning.",
          "vergunning": "splitsingsvergunning",
          "min_opp_m2": 80,
          "max_units": 3,
          "min_per_unit_m2": 18,
          "opp_per_unit": 58.0,
          "bijzonderheden": "Splitsingsvergunning vereist. Min 80m2 totaal, max 3 units. Elke unit min 18m2. Leefbaarheidstoets in kwetsbare wijken. Parkeereis kan van toepassing zijn."
        },
        "opbouwen": {
          "mag_opbouwen": null,
          "uitleg": "Woningtype '' niet gevonden voor Rotterdam. Bekende types: tussenwoning, hoekwoning, twee_onder_een_kap, vrijstaand, appartement.",
          "max_hoogte_m": null,
          "max_verdiepingen": null,
          "dakopbouw_toegestaan": null,
          "ruimte_over_m": null,
          "bijzonderheden": "Rotterdam is relatief soepel met opbouwen. Dakopbouw vergunningvrij onder voorwaarden. Welstandsnota Rotterdam: gebiedsafhankelijk."
        },
        "looptijd_detail": {
          "totaal_maanden": 7,
          "vergunning_maanden": 1,
          "verbouw_maanden": 4.4,
          "verkoop_maanden": 2,
          "type": "medium"
        },
        "validatie": {
          "goedgekeurd": true,
          "onze_pm2": 4718,
          "bronnen": {},
          "gem_extern_pm2": 0,
          "afwijking_pct": 0,
          "gecorrigeerde_pm2": 4718,
          "reden": "Geen externe bronnen beschikbaar"
        }
      }
    },
    {
      "adres": "Mauritsplaats 28",
      "stad": "Rotterdam",
      "postcode": "3012CD",
      "wijk": "Cool",
      "prijs": 325000,
      "opp_m2": 77,
      "prijs_per_m2": 4221.0,
      "type_woning": "apartment",
      "bouwjaar": 1985,
      "energie_label": "A",
      "kamers": 3,
      "source": "funda",
      "url": "https://www.funda.nl/detail/koop/rotterdam/mauritsplaats-28/89776933/",
      "foto_url": "https://cloud.funda.nl/valentina_media/227/471/312.jpg",
      "foto_urls": [
        "https://cloud.funda.nl/valentina_media/227/471/312.jpg",
        "https://cloud.funda.nl/valentina_media/227/471/081.jpg",
        "https://cloud.funda.nl/valentina_media/227/471/083.jpg",
        "https://cloud.funda.nl/valentina_media/227/471/191.jpg",
        "https://cloud.funda.nl/valentina_media/227/471/235.jpg",
        "https://cloud.funda.nl/valentina_media/227/471/085.jpg"
      ],
      "strategie": "fix_flip",
      "marge_pct": 24.0,
      "winst_euro": 125131,
      "roi_pct": 31.6,
      "totale_kosten": 396305,
      "verwachte_opbrengst": 521437,
      "score": 5,
      "is_opknapper": false,
      "calc": {
        "vraagprijs": 325000,
        "ovb_pct": 8.0,
        "ovb": 26000,
        "notaris_makelaar_aankoop": 4225,
        "aankoop_totaal": 355225,
        "renovatie_per_m2": 405,
        "renovatie_detail": {
          "componenten": [
            {
              "naam": "Keuken opfrissen",
              "kosten": 8000,
              "reden": "Nieuwe fronten, werkblad, apparatuur behouden"
            },
            {
              "naam": "Badkamer opfrissen",
              "kosten": 7000,
              "reden": "Sanitair + kranen vervangen, voegen vernieuwen"
            },
            {
              "naam": "Toilet opknappen",
              "kosten": 2500,
              "reden": "Nieuwe WC pot, fontein, kleine tegelreparaties"
            },
            {
              "naam": "Vloeren (50/m²)",
              "kosten": 3850,
              "reden": "Nieuwe PVC click vloer leggen"
            },
            {
              "naam": "Schilderwerk (20/m²)",
              "kosten": 1540,
              "reden": "Latex muren en plafonds"
            },
            {
              "naam": "Elektra check + uitbreiden",
              "kosten": 1500,
              "reden": "Keuring + extra groepen/stopcontacten"
            },
            {
              "naam": "Buitenschilderwerk",
              "kosten": 2500,
              "reden": "Kozijnen buiten schilderen"
            },
            {
              "naam": "Onvoorzien (10%)",
              "kosten": 2689,
              "reden": "Buffer voor verrassingen (asbest, fundering, verborgen gebreken)"
            },
            {
              "naam": "Architect + leges (6%)",
              "kosten": 1613,
              "reden": "Ontwerp, vergunning, bouwbegeleiding"
            }
          ],
          "totaal": 31192,
          "per_m2": 405,
          "onvoorzien_pct": 10
        },
        "bouw_totaal": 31192,
        "looptijd_maanden": 4,
        "rente_pct": 8.0,
        "financiering_basis": 370821,
        "rente": 9888,
        "totaal_kosten": 396305,
        "verkoop_m2": 6908,
        "verkoop_bron": "referentie",
        "referenties": [
          {
            "adres": "Westblaak 32",
            "prijs": 456000,
            "opp_m2": 62,
            "prijs_per_m2": 7355,
            "energie_label": "A+++",
            "type": "apartment",
            "wijk": "Cool",
            "url": "https://www.funda.nl/detail/koop/rotterdam/appartement-westblaak-32-q02/89726223/"
          },
          {
            "adres": "Schiedamsesingel 133",
            "prijs": 579500,
            "opp_m2": 79,
            "prijs_per_m2": 7335,
            "energie_label": "A",
            "type": "apartment",
            "wijk": "Cool",
            "url": "https://www.funda.nl/detail/koop/rotterdam/appartement-schiedamsesingel-133-b/89745555/"
          },
          {
            "adres": "Westblaak 32",
            "prijs": 552000,
            "opp_m2": 76,
            "prijs_per_m2": 7263,
            "energie_label": "A+++",
            "type": "apartment",
            "wijk": "Cool",
            "url": "https://www.funda.nl/detail/koop/rotterdam/appartement-westblaak-32-a01/89716502/"
          },
          {
            "adres": "Kruisplein 986",
            "prijs": 515000,
            "opp_m2": 76,
            "prijs_per_m2": 6776,
            "energie_label": "A",
            "type": "apartment",
            "wijk": "Cool",
            "url": "https://www.funda.nl/detail/koop/rotterdam/appartement-kruisplein-986/43318110/"
          },
          {
            "adres": "Karel Doormanstraat 386",
            "prijs": 615000,
            "opp_m2": 93,
            "prijs_per_m2": 6613,
            "energie_label": "A+",
            "type": "apartment",
            "wijk": "Cool",
            "url": "https://www.funda.nl/detail/koop/rotterdam/appartement-karel-doormanstraat-386-h/43245367/"
          }
        ],
        "bruto_verkoopprijs": 531916,
        "makelaar_verkoop": 7978,
        "notaris_verkoop": 2500,
        "verkoop_kosten": 10478,
        "netto_opbrengst": 521437,
        "winst": 125131,
        "marge_pct": 24.0,
        "roi_pct": 31.6,
        "bod_korting_pct": 10,
        "bod": 292500,
        "bod_totaal_investering": 359835,
        "bod_winst": 161601,
        "bod_marge_pct": 31.0,
        "splitsen": {
          "mag_splitsen": false,
          "uitleg": "Splitsen is waarschijnlijk NIET toegestaan in Rotterdam. Totaal oppervlak (77m2) is kleiner dan minimaal vereist (80m2). Vereist: splitsingsvergunning.",
          "vergunning": "splitsingsvergunning",
          "min_opp_m2": 80,
          "max_units": 3,
          "min_per_unit_m2": 18,
          "opp_per_unit": 38.5,
          "bijzonderheden": "Splitsingsvergunning vereist. Min 80m2 totaal, max 3 units. Elke unit min 18m2. Leefbaarheidstoets in kwetsbare wijken. Parkeereis kan van toepassing zijn."
        },
        "opbouwen": {
          "mag_opbouwen": null,
          "uitleg": "Woningtype 'apartment' niet gevonden voor Rotterdam. Bekende types: tussenwoning, hoekwoning, twee_onder_een_kap, vrijstaand, appartement.",
          "max_hoogte_m": null,
          "max_verdiepingen": null,
          "dakopbouw_toegestaan": null,
          "ruimte_over_m": null,
          "bijzonderheden": "Rotterdam is relatief soepel met opbouwen. Dakopbouw vergunningvrij onder voorwaarden. Welstandsnota Rotterdam: gebiedsafhankelijk."
        },
        "looptijd_detail": {
          "totaal_maanden": 4,
          "vergunning_maanden": 0,
          "verbouw_maanden": 2.0,
          "verkoop_maanden": 2,
          "type": "cosmetisch"
        },
        "funda_prijs_per_m2": "€ 4.221",
        "foto_urls": [
          "https://cloud.funda.nl/valentina_media/227/471/312.jpg",
          "https://cloud.funda.nl/valentina_media/227/471/081.jpg",
          "https://cloud.funda.nl/valentina_media/227/471/083.jpg",
          "https://cloud.funda.nl/valentina_media/227/471/191.jpg",
          "https://cloud.funda.nl/valentina_media/227/471/235.jpg",
          "https://cloud.funda.nl/valentina_media/227/471/085.jpg"
        ],
        "has_garden": false,
        "has_balcony": true,
        "has_roof_terrace": false,
        "has_parking_on_site": false,
        "has_solar_panels": false,
        "has_heat_pump": false,
        "is_monument": false,
        "beschrijving_parsed": {
          "erfpacht": true,
          "vve_bijdrage": 226.0
        },
        "erfpacht": true,
        "vve_bijdrage": 226.0,
        "validatie": {
          "goedgekeurd": false,
          "onze_pm2": 6908,
          "bronnen": {
            "funda_pm2": 4221
          },
          "gem_extern_pm2": 4221,
          "afwijking_pct": 63.7,
          "gecorrigeerde_pm2": 4432,
          "reden": "Onze prijs 64% hoger dan extern (4221/m2). Gecorrigeerd naar 4432/m2"
        }
      }
    }
  ],
  "biedboek": []
}